casetools/__init__.py
casetools-1.0.1.dist-info/licenses/LICENSE
casetools-1.0.1.dist-info/METADATA
casetools-1.0.1.dist-info/WHEEL
casetools-1.0.1.dist-info/top_level.txt
casetools-1.0.1.dist-info/RECORD
