Metadata-Version: 2.4
Name: casetools
Version: 1.0.1
Summary: A lightweight library for controlling text.
Author: Johnathan31
License: MIT
Project-URL: Homepage, https://github.com/johnathan31/casetools
Requires-Python: >=3.8
License-File: LICENSE
Dynamic: license-file
